{"By5BiGHI67HBl2Xo7KQNsA==":"bg1-1920x1280.jpg","rPHo2GPQdSR4H2dAcIlSvw==":"ect24.jpg","sWObPjx4DbctN/4m+p2+GA==":"ect10.jpg","VbLVBCbrwn6PofrgUYujLQ==":"ect11.jpg","teeqjEYT1edVBOp4H0G5sA==":"ect14.jpg","W45WoDY8r0PzihXbKA8kng==":"ect1.jpg","VABDqK7IBk+Sr3fMLcbMpA==":"ect25.jpg","vRu3Pp9loOD712w48zC/2A==":"header-656x437.jpg","HM1ZFbtNWx8n0eXOpcuLmg==":"features-888x592.jpg","egbRWAsSbX2pQwA7ffprUA==":"testimonials-888x592.jpg","eJfP7zUZz/kXkk0hM9v/Fg==":"forms-888x592.jpg","Oksru06Jn3Y0I/Oiu3abfg==":"innovations%20demo%20collage%20-1920x1027.jpg","7EiJAAVMi6D9/3x4amxYrQ==":"data__img-696x463.jpg","LeiJcxM87MAFMmm2yOtL7w==":"science__img-696x473.jpg","Rd5wcnmHbYYzGfsABASZ3w==":"bg2-1920x1280.jpg"}